rabbitmqresources/__init__.py
rabbitmqresources/worker.py
rabbitmqresources/tasks/__init__.py
rabbitmqresources/tasks/tasks.py
rabbitmq_email_notifier-0.0.6.dist-info/LICENSE
rabbitmq_email_notifier-0.0.6.dist-info/METADATA
rabbitmq_email_notifier-0.0.6.dist-info/WHEEL
rabbitmq_email_notifier-0.0.6.dist-info/top_level.txt
rabbitmq_email_notifier-0.0.6.dist-info/RECORD
