Metadata-Version: 2.1
Name: rabbitmq-email-notifier
Version: 0.0.6
Summary: A set of utilities for placing a message onto a queue for an emailer listener to receive
Home-page: https://github.com/harvard-lts/rabbitmq-email-notifier
Author: Chip Goines
Author-email: chip_goines@harvard.edu
Classifier: Programming Language :: Python :: 3
Classifier: License :: OSI Approved :: MIT License
Classifier: Operating System :: OS Independent
Requires-Python: >=3.6
License-File: LICENSE
Requires-Dist: celery (==5.2.7)
Requires-Dist: certifi (==2023.7.22)
Requires-Dist: coverage (==7.2.6)
Requires-Dist: iniconfig (==2.0.0)
Requires-Dist: lxml (==4.9.2)
Requires-Dist: opentelemetry-api (==1.19.0)
Requires-Dist: opentelemetry-sdk (==1.19.0)
Requires-Dist: opentelemetry-exporter-jaeger (==1.19.0)
Requires-Dist: opentelemetry-exporter-otlp-proto-grpc (==1.19.0)
Requires-Dist: opentelemetry-semantic-conventions (==0.40b0)
Requires-Dist: packaging (==23.1)
Requires-Dist: pika (==1.3.2)
Requires-Dist: pluggy (==1.0.0)
Requires-Dist: project-paths (==1.1.1)
Requires-Dist: pytest (==7.3.1)
Requires-Dist: pytest-mock (==3.10.0)
Requires-Dist: python-dotenv (==1.0.0)
Requires-Dist: requests (==2.31.0)
Requires-Dist: requests-mock (==1.10.0)
Requires-Dist: retrying (==1.3.4)
Requires-Dist: toml (==0.10.2)
Requires-Dist: tomli (==2.0.1)
Requires-Dist: twine (==4.0.2)
Requires-Dist: urllib3 (==2.0.2)
